microfilm/__init__.py
microfilm/_version.py
microfilm/colorify.py
microfilm/microanim.py
microfilm/microplot.py
microfilm/dataset/__init__.py
microfilm/dataset/dataset.py
microfilm-0.3.0.dist-info/LICENSE
microfilm-0.3.0.dist-info/METADATA
microfilm-0.3.0.dist-info/WHEEL
microfilm-0.3.0.dist-info/top_level.txt
microfilm-0.3.0.dist-info/RECORD
