Metadata-Version: 2.1
Name: microfilm
Version: 0.3.0
Summary: Creating figures and animations for multi-channel images with a focus on microscopy.
Home-page: https://github.com/guiwitz/microfilm
Author: Guillaume Witz
Author-email: guillaume.witz@math.unibe.ch
License: BSD 3-Clause
Classifier: Development Status :: 3 - Alpha
Classifier: Intended Audience :: Education
Classifier: Intended Audience :: Science/Research
Classifier: License :: OSI Approved :: BSD License
Classifier: Programming Language :: Python
Classifier: Programming Language :: Python :: 3 :: Only
Classifier: Programming Language :: Python :: 3.9
Classifier: Programming Language :: Python :: 3.10
Classifier: Programming Language :: Python :: 3.11
Classifier: Programming Language :: Python :: 3.12
Classifier: Topic :: Scientific/Engineering
Classifier: Topic :: Scientific/Engineering :: Visualization
Classifier: Topic :: Scientific/Engineering :: Information Analysis
Classifier: Topic :: Scientific/Engineering :: Bio-Informatics
Classifier: Topic :: Utilities
Classifier: Operating System :: Microsoft :: Windows
Classifier: Operating System :: POSIX
Classifier: Operating System :: Unix
Classifier: Operating System :: MacOS
Requires-Python: >=3.9
License-File: LICENSE
Requires-Dist: cmap
Requires-Dist: h5py
Requires-Dist: imageio
Requires-Dist: matplotlib
Requires-Dist: matplotlib-scalebar
Requires-Dist: natsort
Requires-Dist: numpy
Requires-Dist: scikit-image
Requires-Dist: tifffile
Requires-Dist: xarray
Provides-Extra: multipage
Requires-Dist: bioio; extra == "multipage"
Requires-Dist: bioio-tifffile; extra == "multipage"
Provides-Extra: nd2
Requires-Dist: nd2reader; extra == "nd2"
Provides-Extra: animation
Requires-Dist: imageio-ffmpeg; extra == "animation"
Requires-Dist: ipywidgets; extra == "animation"
Provides-Extra: all
Requires-Dist: bioio; extra == "all"
Requires-Dist: bioio-tifffile; extra == "all"
Requires-Dist: imageio-ffmpeg; extra == "all"
Requires-Dist: ipywidgets; extra == "all"
Requires-Dist: nd2reader; extra == "all"
